gvmtools/__init__.py
gvmtools/__version__.py
gvmtools/cli.py
gvmtools/config.py
gvmtools/helper.py
gvmtools/parser.py
gvmtools/pyshell.py
gvmtools/script.py
gvm_tools-25.4.2.dist-info/METADATA
gvm_tools-25.4.2.dist-info/WHEEL
gvm_tools-25.4.2.dist-info/entry_points.txt
gvm_tools-25.4.2.dist-info/licenses/LICENSE
gvm_tools-25.4.2.dist-info/RECORD
