Metadata-Version: 2.4
Name: gvm-tools
Version: 25.4.2
Summary: Tools to control a GSM/GVM over GMP or OSP
License: GPL-3.0-or-later
License-File: LICENSE
Author: Greenbone AG
Author-email: info@greenbone.net
Requires-Python: >=3.9.2,<4.0.0
Classifier: Development Status :: 5 - Production/Stable
Classifier: Environment :: Console
Classifier: Intended Audience :: Developers
Classifier: Intended Audience :: System Administrators
Classifier: License :: OSI Approved :: GNU General Public License v3 (GPLv3)
Classifier: License :: OSI Approved :: GNU General Public License v3 or later (GPLv3+)
Classifier: Operating System :: OS Independent
Classifier: Programming Language :: Python :: 3
Classifier: Programming Language :: Python :: 3.10
Classifier: Programming Language :: Python :: 3.11
Classifier: Programming Language :: Python :: 3.12
Classifier: Programming Language :: Python :: 3.13
Classifier: Programming Language :: Python :: 3.14
Classifier: Programming Language :: Python :: 3.9
Classifier: Topic :: Software Development :: Libraries :: Python Modules
Requires-Dist: python-gvm (>=26.0.0)
Project-URL: Documentation, https://greenbone.github.io/gvm-tools/
Project-URL: Homepage, https://github.com/greenbone/gvm-tools/
Project-URL: Repository, https://github.com/greenbone/gvm-tools/
